lotek_rpc/__init__.py
lotek_rpc/api.py
lotek_rpc/constants.py
lotek_rpc/selfsigned.cert
lotek_rpc-1.1.0.dist-info/LICENSE
lotek_rpc-1.1.0.dist-info/METADATA
lotek_rpc-1.1.0.dist-info/WHEEL
lotek_rpc-1.1.0.dist-info/top_level.txt
lotek_rpc-1.1.0.dist-info/RECORD
