Metadata-Version: 2.1
Name: lotek-rpc
Version: 1.1.0
Summary: Simple TCP client impl to interact with the irc bot and build remote plugins.
Home-page: https://github.com/mnemonicmane/irc_bot
Author: anonymous
Author-email: internetrelaychatter@proton.me
License: WTFPL-2.0
Project-URL: Bug Tracker, https://github.com/mnemonicmane/irc_bot/issues
Platform: UNKNOWN
Classifier: Programming Language :: Python :: 3
Requires-Python: >=3.7
